boa/__init__.py
boa/coverage.py
boa/debugger.py
boa/environment.py
boa/explorer.py
boa/interpret.py
boa/ipython.py
boa/network.py
boa/precompile.py
boa/profiling.py
boa/rpc.py
boa/contracts/__init__.py
boa/contracts/base_evm_contract.py
boa/contracts/abi/__init__.py
boa/contracts/abi/abi_contract.py
boa/contracts/vyper/__init__.py
boa/contracts/vyper/ast_utils.py
boa/contracts/vyper/compiler_utils.py
boa/contracts/vyper/decoder_utils.py
boa/contracts/vyper/event.py
boa/contracts/vyper/ir_executor.py
boa/contracts/vyper/vyper_contract.py
boa/integrations/__init__.py
boa/integrations/jupyter/__init__.py
boa/integrations/jupyter/browser.py
boa/integrations/jupyter/constants.py
boa/integrations/jupyter/handlers.py
boa/integrations/jupyter/jupyter.js
boa/integrations/jupyter/utils.py
boa/test/__init__.py
boa/test/plugin.py
boa/test/strategies.py
boa/util/abi.py
boa/util/disk_cache.py
boa/util/eip1167.py
boa/util/eip5202.py
boa/util/evm.py
boa/util/exceptions.py
boa/util/leveldb.py
boa/util/lrudict.py
boa/vm/fast_accountdb.py
boa/vm/fast_mem.py
boa/vm/fork.py
boa/vm/gas_meters.py
boa/vm/py_evm.py
boa/vm/utils.py
curve_boa-0.2.0.0.dist-info/LICENSE
curve_boa-0.2.0.0.dist-info/METADATA
curve_boa-0.2.0.0.dist-info/WHEEL
curve_boa-0.2.0.0.dist-info/entry_points.txt
curve_boa-0.2.0.0.dist-info/top_level.txt
curve_boa-0.2.0.0.dist-info/RECORD
