Metadata-Version: 2.1
Name: curve-boa
Version: 0.2.0.0
Summary: A Vyper interpreter
License: Copyright 2022 Charles Cooper
Keywords: ethereum,evm,smart contract,development
Classifier: Topic :: Software Development
License-File: LICENSE
Requires-Dist: vyper>=0.4.0
Requires-Dist: eth-stdlib<0.3.0,>=0.2.7
Requires-Dist: eth-abi
Requires-Dist: py-evm>=0.10.0b4
Requires-Dist: eth-typing
Requires-Dist: hypothesis
Requires-Dist: pytest
Requires-Dist: pytest-cov
Requires-Dist: typing-extensions
Requires-Dist: rich
Requires-Dist: requests
Requires-Dist: eth-account>=0.13.0
Provides-Extra: colab
Requires-Dist: ipykernel>=6.29.4; extra == "colab"
Provides-Extra: forking-recommended
Requires-Dist: ujson; extra == "forking-recommended"
